inteltk/__init__.py
inteltk/colors.py
inteltk/inteltk.py
inteltk-1.0.1.dist-info/LICENSE
inteltk-1.0.1.dist-info/METADATA
inteltk-1.0.1.dist-info/WHEEL
inteltk-1.0.1.dist-info/top_level.txt
inteltk-1.0.1.dist-info/RECORD
