Metadata-Version: 2.1
Name: inteltk
Version: 1.0.1
Summary: A toolkit for creating interactive shells
Author-email: Martin Kovács <martin.k.kovacs@gmail.com>
Project-URL: Homepage, https://github.com/martinkovacs/inteltk
Classifier: Programming Language :: Python :: 3
Classifier: License :: OSI Approved :: MIT License
Classifier: Operating System :: OS Independent
Requires-Python: >=3.10
License-File: LICENSE
Requires-Dist: pyreadline3 (>=3.4.1) ; platform_version == "Windows"
